homunculo.py
homunculo-0.1.dist-info/LICENSE
homunculo-0.1.dist-info/WHEEL
homunculo-0.1.dist-info/METADATA
homunculo-0.1.dist-info/RECORD
